pkgman/__init__.py
pkgman-0.1.1.dist-info/licenses/LICENSE
pkgman-0.1.1.dist-info/METADATA
pkgman-0.1.1.dist-info/WHEEL
pkgman-0.1.1.dist-info/entry_points.txt
pkgman-0.1.1.dist-info/top_level.txt
pkgman-0.1.1.dist-info/RECORD
