Metadata-Version: 2.4
Name: pkgman
Version: 0.1.1
Summary: Install and import all packages in two lines.
Author-email: Rongxin <rongxin@u.nus.edu>
Project-URL: Homepage, https://github.com/reycn/pkgman
Classifier: Programming Language :: Python :: 3
Classifier: Operating System :: OS Independent
Requires-Python: >=3.8
License-File: LICENSE
Dynamic: license-file
